README.rst
setup.cfg
setup.py
niftyclient/__init__.py
niftyclient/c2b.py
niftyclient/client_base.py
niftyclient/exceptions.py
niftyclient/nifty_client.py
niftyclient/online_checkout.py
niftyclient/schema.py
niftyclient/signed_request_auth.py
niftyclient/wallet.py
niftyclient.egg-info/PKG-INFO
niftyclient.egg-info/SOURCES.txt
niftyclient.egg-info/dependency_links.txt
niftyclient.egg-info/not-zip-safe
niftyclient.egg-info/requires.txt
niftyclient.egg-info/top_level.txt