Metadata-Version: 1.1
Name: niftyclient
Version: 0.2.3
Summary: Official Python API client for Nifty
Home-page: https://bitbucket.org/east36/python-nifty-client
Author: Laban Mwangi
Author-email: lmwangi@east36.co.ke
License: GPLv3
Platform: any
Classifier: Development Status :: 4 - Beta
Classifier: Environment :: Web Environment
Classifier: Intended Audience :: Developers
Classifier: License :: OSI Approved :: BSD License
Classifier: Operating System :: OS Independent
Classifier: Programming Language :: Python
Classifier: Topic :: Internet :: WWW/HTTP :: Dynamic Content
Classifier: Topic :: Software Development :: Libraries :: Python Modules
